adder/fa.v
module full_adder(a,b,c,s,cout);
	input a,b,c;
	output s,cout;
	assign s=a^b^c;
	assign cout=(a&b)|(b&c)|(c&a);
endmodule

adder/fa_test.v
module testbench;
	reg a,b,c;
	wire sum,cout;
	integer i;
full_adder FA(a,b,c,sum,cout);
	initial 
		begin	
			$dumpfile("fadder.vcd");
			$dumpvars(0,testbench);
			for(i=0;i<8;i=i+1)
			begin
			{a,b,c}=i; #5;
			$display("T=%2d, a=%b, b=%b, c=%b, sum=%b, cout=%b",$time,a,b,c,sum,cout);
end
#5 $finish;
end
endmodule

adder/fadder.vcd
$date
	Sun Jun 02 16:49:02 2024
$end
$version
	Icarus Verilog
$end
$timescale
	1s
$end
$scope module testbench $end
$var wire 1 ! sum $end
$var wire 1 " cout $end
$var reg 1 # a $end
$var reg 1 $ b $end
$var reg 1 % c $end
$var integer 32 & i [31:0] $end
$scope module FA $end
$var wire 1 # a $end
$var wire 1 $ b $end
$var wire 1 % c $end
$var wire 1 " cout $end
$var wire 1 ! s $end
$upscope $end
$upscope $end
$enddefinitions $end
$comment Show the parameter values. $end
$dumpall
$end
#0
$dumpvars
b0 &
0%
0$
0#
0"
0!
$end
#5
1!
1%
b1 &
#10
1!
1$
0%
b10 &
#15
1"
0!
1%
b11 &
#20
0"
1!
1#
0$
0%
b100 &
#25
1"
0!
1%
b101 &
#30
1"
0!
1$
0%
b110 &
#35
1!
1%
b111 &
#40
b1000 &
