counter/counter.v

module counter (clear, clock , count);
	parameter N=7;
	input clear, clock;
	output reg [0:N] count;
	always@(negedge clock)
		if(clear)
		count<=0;
		else
		count <= count +1;
endmodule

counter/count_tb.v

module test_counter;
	reg clk,clr;
	wire [7:0] out;
	
	counter CNT (clr,clk,out);
	
	initial clk=1'b0;
	
	always  #5 clk = ~clk ;
	
	initial
		begin 
			clr = 1'b1;
			#15 clr = 1'b0;
			#200 clr = 1'b1;
			#10 $finish;
		end
	
	initial 
		begin
			$dumpfile("counter.vcd");
			$dumpvars(0,test_counter);
			$monitor($time,"count= %d",out);
		end
endmodule

counter/counter.vcd
$date
	Sat Jun 08 20:59:11 2024
$end
$version
	Icarus Verilog
$end
$timescale
	1s
$end
$scope module test_counter $end
$var wire 8 ! out [7:0] $end
$var reg 1 " clk $end
$var reg 1 # clr $end
$scope module CNT $end
$var wire 1 # clear $end
$var wire 1 " clock $end
$var parameter 32 $ N $end
$var reg 8 % count [0:7] $end
$upscope $end
$upscope $end
$enddefinitions $end
$comment Show the parameter values. $end
$dumpall
b111 $
$end
#0
$dumpvars
b0 %
1#
0"
b0 !
$end
#5
1"
#10
0"
#15
1"
0#
#20
b1 !
b1 %
0"
#25
1"
#30
b10 !
b10 %
0"
#35
1"
#40
b11 !
b11 %
0"
#45
1"
#50
b100 !
b100 %
0"
#55
1"
#60
b101 !
b101 %
0"
#65
1"
#70
b110 !
b110 %
0"
#75
1"
#80
b111 !
b111 %
0"
#85
1"
#90
b1000 !
b1000 %
0"
#95
1"
#100
b1001 !
b1001 %
0"
#105
1"
#110
b1010 !
b1010 %
0"
#115
1"
#120
b1011 !
b1011 %
0"
#125
1"
#130
b1100 !
b1100 %
0"
#135
1"
#140
b1101 !
b1101 %
0"
#145
1"
#150
b1110 !
b1110 %
0"
#155
1"
#160
b1111 !
b1111 %
0"
#165
1"
#170
b10000 !
b10000 %
0"
#175
1"
#180
b10001 !
b10001 %
0"
#185
1"
#190
b10010 !
b10010 %
0"
#195
1"
#200
b10011 !
b10011 %
0"
#205
1"
#210
b10100 !
b10100 %
0"
#215
1"
1#
#220
b0 !
b0 %
0"
