shift_register/shift_reg.v

module shiftreg4bit(clock,clear,A,E);
	input clock,A,clear;
	output reg E;
	reg B,C,D;
	always@(posedge clock or negedge clear)
		begin
		if(!clear) begin B<=0; C<=0; D<=0; E<=0; end
		else
			begin
			E<=D;
			D<=C;
			C<=B;
			B<=A;
			end
		end
endmodule

shift_register/shift_test.v

module shift_test;
	reg clk,clear,in;
	wire out;
	integer i;
	shiftreg4bit test_sr(clk,clear,in,out);
	
	initial
		begin clk = 1'b0; #2 clear = 0; #5 clear = 1; end
	
	always #5 clk = ~clk;
	
	initial begin #2;
		repeat (2)
		begin #10 in=0; #10 in=0; #10 in=1; #10 in=1; end
		end
	
	initial
		begin
			$dumpfile ("shifter.vcd");
			$dumpvars (0,shift_test);
			#200 $finish;
		end 
endmodule

shift_register/shifter.vcd
$date
	Sat Jun 08 17:52:02 2024
$end
$version
	Icarus Verilog
$end
$timescale
	1s
$end
$scope module shift_test $end
$var wire 1 ! out $end
$var reg 1 " clear $end
$var reg 1 # clk $end
$var reg 1 $ in $end
$scope module test_sr $end
$var wire 1 $ A $end
$var wire 1 " clear $end
$var wire 1 # clock $end
$var reg 1 % B $end
$var reg 1 & C $end
$var reg 1 ' D $end
$var reg 1 ! E $end
$upscope $end
$upscope $end
$enddefinitions $end
$comment Show the parameter values. $end
$dumpall
$end
#0
$dumpvars
x'
x&
x%
x$
0#
x"
x!
$end
#2
0!
0'
0&
0%
0"
#5
1#
#7
1"
#10
0#
#12
0$
#15
1#
#20
0#
#25
1#
#30
0#
#32
1$
#35
1%
1#
#40
0#
#45
1&
1#
#50
0#
#52
0$
#55
0%
1'
1#
#60
0#
#65
0&
1!
1#
#70
0#
#72
1$
#75
1%
0'
1#
#80
0#
#85
1&
0!
1#
#90
0#
#95
1'
1#
#100
0#
#105
1!
1#
